.travis.yml
CHANGES.rst
MANIFEST.in
README.rst
setup.cfg
setup.py
for_beginner_piano.egg-info/PKG-INFO
for_beginner_piano.egg-info/SOURCES.txt
for_beginner_piano.egg-info/dependency_links.txt
for_beginner_piano.egg-info/entry_points.txt
for_beginner_piano.egg-info/not-zip-safe
for_beginner_piano.egg-info/requires.txt
for_beginner_piano.egg-info/top_level.txt
piano/__init__.py
piano/cli.py