Metadata-Version: 1.1
Name: for-beginner-piano
Version: 0.3.0
Summary: Piano. Beginner friendly Plone development.
Home-page: https://github.com/for-beginner-piano/for-beginner-piano
Author: David Bain
Author-email: david@alteroo.com
License: BSD
Platform: Linux
Platform: Mac
Classifier: Development Status :: 4 - Beta
Classifier: Environment :: Console
Classifier: Intended Audience :: Developers
Classifier: License :: OSI Approved :: BSD License
Classifier: Operating System :: POSIX
Classifier: Operating System :: MacOS
Classifier: Operating System :: Unix
Classifier: Framework :: Plone :: 4.3
Classifier: Programming Language :: Python
Classifier: Programming Language :: Python :: 2.7
Classifier: Topic :: Software Development :: Libraries :: Python Modules
